Metadata-Version: 2.1
Name: django-fast-paginator
Version: 1.0.4
Summary: A Django app to paginate querysets faster.
Home-page: https://github.com/bilbeyt/django-fast-pagination
Author: Tolga Bilbey
Author-email: bilbeyt@gmail.com
License: MIT
Download-URL: https://github.com/bilbeyt/django-fast-pagination/archive/v1.0.4.tar.gz
Keywords: django,pagination,optimization
Platform: any
Classifier: Environment :: Web Environment
Classifier: Framework :: Django
Classifier: Framework :: Django :: 2.2
Classifier: Framework :: Django :: 3.0
Classifier: Intended Audience :: Developers
Classifier: License :: OSI Approved :: MIT License
Classifier: Operating System :: OS Independent
Classifier: Programming Language :: Python
Classifier: Programming Language :: Python :: 3
Classifier: Programming Language :: Python :: 3 :: Only
Classifier: Programming Language :: Python :: 3.6
Classifier: Programming Language :: Python :: 3.7
Classifier: Programming Language :: Python :: 3.8
Classifier: Topic :: Internet :: WWW/HTTP
Classifier: Topic :: Internet :: WWW/HTTP :: Dynamic Content
Requires-Python: >= 3.0.0
